atoti_directquery_jdbc/__init__.py
atoti_directquery_jdbc/connection_config.py
atoti_directquery_jdbc/py.typed
atoti_directquery_jdbc/table_config.py
atoti_client_directquery_jdbc-0.9.12.dist-info/WHEEL
atoti_client_directquery_jdbc-0.9.12.dist-info/METADATA
atoti_client_directquery_jdbc-0.9.12.dist-info/RECORD
