Metadata-Version: 2.3
Name: atoti-client-directquery-jdbc
Version: 0.9.12
Summary: Code to use DirectQuery through JDBC
Keywords: atoti,cloud,database,directquery,jdbc
Author: ActiveViam
Author-email: ActiveViam <atoti-dev@activeviam.com>
Classifier: Development Status :: 4 - Beta
Classifier: License :: Free for non-commercial use
Classifier: Operating System :: OS Independent
Classifier: Programming Language :: Python :: 3
Classifier: Typing :: Typed
Requires-Dist: atoti-client==0.9.12
Requires-Dist: pydantic>=2.12.3
Requires-Dist: typing-extensions>=4.15.0
Requires-Python: >=3.10
Project-URL: Documentation, https://docs.activeviam.com/products/atoti/python-sdk/0.9.12/api/atoti_directquery_jdbc.html
Project-URL: Homepage, https://www.atoti.io
Project-URL: Issues, https://github.com/atoti/atoti/issues
